<?xml version="1.0" encoding="UTF-8" ?>

 <!DOCTYPE tiles-definitions PUBLIC
       "-//Apache Software Foundation//DTD Tiles Configuration 1.1//EN"
       "http://jakarta.apache.org/struts/dtds/tiles-config_1_1.dtd">

<tiles-definitions>

    <definition name="index.page" path="/pages/layouts/main-layout.jsp">
        <put name="header" value="/pages/tiles/header.jsp"/>
        <put name="menu" value="/pages/tiles/menu.jsp"/>
        <put name="body" value="/pages/tiles/welcome.jsp"/>
        <put name="footer" value="/pages/tiles/footer.jsp"/>
    </definition>
    <definition name="newslist.page" extends="index.page">
        <put name="body" value="/pages/tiles/newslist.jsp"/>
    </definition>
    <definition name="newsview.page" extends="index.page">
        <put name="body" value="/pages/tiles/newsview.jsp"/>
    </definition>
    <definition name="newsedit.page" extends="index.page">
        <put name="body" value="/pages/tiles/newsedit.jsp"/>
    </definition>

</tiles-definitions>
